{
  "devnet": {
    "escrow-rust": {
      "codeHash": "0x6a52643df87e360ffe4ea084b8054f07d3fd4f729a4728a40ad11abdb340a814",
      "hashType": "data2",
      "cellDeps": [
        {
          "cellDep": {
            "outPoint": {
              "txHash": "0xb39f530bf452b4e897a12313699a0b051c81e175351a8f67edf61cd653900849",
              "index": 0
            },
            "depType": "code"
          }
        }
      ]
    }
  },
  "testnet": {
    "escrow-rust": {
      "codeHash": "0x6a52643df87e360ffe4ea084b8054f07d3fd4f729a4728a40ad11abdb340a814",
      "hashType": "data2",
      "cellDeps": [
        {
          "cellDep": {
            "outPoint": {
              "txHash": "0xaf67f44b713734525f11717a82a3f10eba0bf88791d437748726f973ac7a4a7b",
              "index": 0
            },
            "depType": "code"
          }
        }
      ]
    }
  },
  "mainnet": {}
}